mlserver_sklearn/__init__.py
mlserver_sklearn/sklearn.py
mlserver_sklearn/version.py
mlserver_sklearn-1.7.1.dist-info/LICENSE
mlserver_sklearn-1.7.1.dist-info/METADATA
mlserver_sklearn-1.7.1.dist-info/WHEEL
mlserver_sklearn-1.7.1.dist-info/RECORD
