Metadata-Version: 2.3
Name: mlserver-sklearn
Version: 1.7.1
Summary: Scikit-Learn runtime for MLServer
License: Apache-2.0
Author: Seldon Technologies Ltd.
Author-email: hello@seldon.io
Requires-Python: >=3.9,<3.13
Classifier: License :: OSI Approved :: Apache Software License
Classifier: Programming Language :: Python :: 3
Classifier: Programming Language :: Python :: 3.9
Classifier: Programming Language :: Python :: 3.10
Classifier: Programming Language :: Python :: 3.11
Classifier: Programming Language :: Python :: 3.12
Requires-Dist: joblib
Requires-Dist: mlserver
Requires-Dist: scikit-learn
